canonicalwebteam/__init__.py
canonicalwebteam/directory_parser/__init__.py
canonicalwebteam/directory_parser/app.py
canonicalwebteam/directory_parser/templates/sitemap_children.xml
canonicalwebteam/directory_parser/templates/sitemap_template.xml
canonicalwebteam_directory_parser-1.2.10.dist-info/licenses/LICENSE
canonicalwebteam_directory_parser-1.2.10.dist-info/METADATA
canonicalwebteam_directory_parser-1.2.10.dist-info/WHEEL
canonicalwebteam_directory_parser-1.2.10.dist-info/top_level.txt
canonicalwebteam_directory_parser-1.2.10.dist-info/RECORD
