Metadata-Version: 2.4
Name: canonicalwebteam.directory-parser
Version: 1.2.10
Summary: Flask extension to parse websites and extract structured data to build sitemaps.
Home-page: https://github.com/canonical/canonicalwebteam.directory-parser
Author: Canonical webteam
Author-email: webteam@canonical.com
License-File: LICENSE
Requires-Dist: Flask>=1.0.2
Requires-Dist: beautifulsoup4
Requires-Dist: humanize
Requires-Dist: lxml
Requires-Dist: requests
Requires-Dist: python-dateutil
Requires-Dist: validators
Requires-Dist: python-slugify
Dynamic: author
Dynamic: author-email
Dynamic: description
Dynamic: description-content-type
Dynamic: home-page
Dynamic: license-file
Dynamic: requires-dist
Dynamic: summary
